README.rst
setup.cfg
setup.py
extract_html_diff/__init__.py
extract_html_diff/diff.py
extract_html_diff/utils.py
extract_html_diff.egg-info/PKG-INFO
extract_html_diff.egg-info/SOURCES.txt
extract_html_diff.egg-info/dependency_links.txt
extract_html_diff.egg-info/requires.txt
extract_html_diff.egg-info/top_level.txt
tests/__init__.py
tests/test_diff.py
tests/test_test_utils.py
tests/utils.py