Metadata-Version: 1.1
Name: extract-html-diff
Version: 0.1.0
Summary: Extract difference between two html pages
Home-page: https://github.com/TeamHG-Memex/extract-html-diff
Author: Konstantin Lopuhin
Author-email: kostia.lopuhin@gmail.com
License: MIT
Platform: UNKNOWN
Classifier: Development Status :: 3 - Alpha
Classifier: Topic :: Internet :: WWW/HTTP :: Indexing/Search
Classifier: License :: OSI Approved :: MIT License
Classifier: Programming Language :: Python
Classifier: Programming Language :: Python :: 3
Classifier: Programming Language :: Python :: 3.5
Classifier: Programming Language :: Python :: 3.6
